{"nodes": [{"id": "src_app_shop_contact_page_tsx", "label": "page.tsx", "file_type": "code", "source_file": "src/app/(shop)/contact/page.tsx", "source_location": "L1"}, {"id": "page_generatemetadata", "label": "generateMetadata()", "file_type": "code", "source_file": "src/app/(shop)/contact/page.tsx", "source_location": "L8"}, {"id": "page_contactpage", "label": "ContactPage()", "file_type": "code", "source_file": "src/app/(shop)/contact/page.tsx", "source_location": "L46"}], "edges": [{"source": "src_app_shop_contact_page_tsx", "target": "pages_actions", "relation": "imports_from", "confidence": "EXTRACTED", "source_file": "src/app/(shop)/contact/page.tsx", "source_location": "L1", "weight": 1.0}, {"source": "src_app_shop_contact_page_tsx", "target": "page_renderer", "relation": "imports_from", "confidence": "EXTRACTED", "source_file": "src/app/(shop)/contact/page.tsx", "source_location": "L2", "weight": 1.0}, {"source": "src_app_shop_contact_page_tsx", "target": "next", "relation": "imports_from", "confidence": "EXTRACTED", "source_file": "src/app/(shop)/contact/page.tsx", "source_location": "L3", "weight": 1.0}, {"source": "src_app_shop_contact_page_tsx", "target": "page_sections", "relation": "imports_from", "confidence": "EXTRACTED", "source_file": "src/app/(shop)/contact/page.tsx", "source_location": "L4", "weight": 1.0}, {"source": "src_app_shop_contact_page_tsx", "target": "page_generatemetadata", "relation": "contains", "confidence": "EXTRACTED", "source_file": "src/app/(shop)/contact/page.tsx", "source_location": "L8", "weight": 1.0}, {"source": "src_app_shop_contact_page_tsx", "target": "page_contactpage", "relation": "contains", "confidence": "EXTRACTED", "source_file": "src/app/(shop)/contact/page.tsx", "source_location": "L46", "weight": 1.0}]}